mypassgen/__init__.py
mypassgen/idgen.py
mypassgen-2.0.0.dist-info/METADATA
mypassgen-2.0.0.dist-info/WHEEL
mypassgen-2.0.0.dist-info/top_level.txt
mypassgen-2.0.0.dist-info/RECORD
