Metadata-Version: 2.1
Name: mypassgen
Version: 2.0.0
Summary: An example of a custom library
Home-page: UNKNOWN
Author: Anup Ghosh
Author-email: anupbsmrstu@gmail.com
License: UNKNOWN
Platform: UNKNOWN
Classifier: Programming Language :: Python :: 3
Classifier: License :: OSI Approved :: MIT License
Classifier: Operating System :: OS Independent
